pywpsrpc/__init__.py
pywpsrpc/bindings/common/common.sip
pywpsrpc/bindings/common/common.toml
pywpsrpc/bindings/common/export.sip
pywpsrpc/bindings/common/guid.sip
pywpsrpc/bindings/common/ksoapi.sip
pywpsrpc/bindings/common/ksoapi/Adjustments.sip
pywpsrpc/bindings/common/ksoapi/AnswerWizard.sip
pywpsrpc/bindings/common/ksoapi/AnswerWizardFiles.sip
pywpsrpc/bindings/common/ksoapi/Assistant.sip
pywpsrpc/bindings/common/ksoapi/Axes.sip
pywpsrpc/bindings/common/ksoapi/Balloon.sip
pywpsrpc/bindings/common/ksoapi/BalloonCheckbox.sip
pywpsrpc/bindings/common/ksoapi/BalloonCheckboxes.sip
pywpsrpc/bindings/common/ksoapi/BalloonLabel.sip
pywpsrpc/bindings/common/ksoapi/BalloonLabels.sip
pywpsrpc/bindings/common/ksoapi/BulletFormat2.sip
pywpsrpc/bindings/common/ksoapi/COMAddIn.sip
pywpsrpc/bindings/common/ksoapi/COMAddIns.sip
pywpsrpc/bindings/common/ksoapi/CalloutFormat.sip
pywpsrpc/bindings/common/ksoapi/CanvasShapes.sip
pywpsrpc/bindings/common/ksoapi/CategoryCollection.sip
pywpsrpc/bindings/common/ksoapi/ChartColorFormat.sip
pywpsrpc/bindings/common/ksoapi/ChartFillFormat.sip
pywpsrpc/bindings/common/ksoapi/ChartFont.sip
pywpsrpc/bindings/common/ksoapi/ChartGroups.sip
pywpsrpc/bindings/common/ksoapi/ChartPoint.sip
pywpsrpc/bindings/common/ksoapi/ColorFormat.sip
pywpsrpc/bindings/common/ksoapi/CommandBar.sip
pywpsrpc/bindings/common/ksoapi/CommandBarControl.sip
pywpsrpc/bindings/common/ksoapi/CommandBarControls.sip
pywpsrpc/bindings/common/ksoapi/CommandBarPopup.sip
pywpsrpc/bindings/common/ksoapi/ConnectorFormat.sip
pywpsrpc/bindings/common/ksoapi/ContactCard.sip
pywpsrpc/bindings/common/ksoapi/Crop.sip
pywpsrpc/bindings/common/ksoapi/CustomTaskPaneEvents.sip
pywpsrpc/bindings/common/ksoapi/CustomXMLNode.sip
pywpsrpc/bindings/common/ksoapi/CustomXMLNodes.sip
pywpsrpc/bindings/common/ksoapi/CustomXMLPrefixMapping.sip
pywpsrpc/bindings/common/ksoapi/CustomXMLPrefixMappings.sip
pywpsrpc/bindings/common/ksoapi/CustomXMLSchema.sip
pywpsrpc-2.3.12.dist-info/WHEEL
pywpsrpc-2.3.12.dist-info/METADATA
pywpsrpc-2.3.12.dist-info/RECORD
