Metadata-Version: 2.1
Name: pywpsrpc
Version: 2.3.12
Requires-Python: >=3.8
Summary: Python bindings for the WPS Office RPC
Home-Page: https://github.com/timxx/pywpsrpc
Author: Weitian Leung
Author-Email: weitianleung@gmail.com
License: MIT
Platform: Linux
